spyse/__init__.py
spyse/client.py
spyse/models.py
spyse/response.py
spyse/search_query.py
spyse_python-2.2.3.dist-info/LICENSE.md
spyse_python-2.2.3.dist-info/METADATA
spyse_python-2.2.3.dist-info/WHEEL
spyse_python-2.2.3.dist-info/top_level.txt
spyse_python-2.2.3.dist-info/RECORD
