Metadata-Version: 2.1
Name: spyse-python
Version: 2.2.3
Summary: Python wrapper for spyse.com
Home-page: https://github.com/spyse-com/spyse-python
Author: Roman Romanov
Author-email: roman.romanov@spyse.com
License: MIT License
Platform: UNKNOWN
License-File: LICENSE.md
